locklib/__init__.py
locklib/errors.py
locklib/py.typed
locklib/locks/__init__.py
locklib/locks/smart_lock/__init__.py
locklib/locks/smart_lock/graph.py
locklib/locks/smart_lock/lock.py
locklib/locks/tracer/__init__.py
locklib/locks/tracer/events.py
locklib/locks/tracer/tracer.py
locklib/protocols/__init__.py
locklib/protocols/async_context_lock.py
locklib/protocols/context_lock.py
locklib/protocols/lock.py
locklib-0.0.18.dist-info/LICENSE
locklib-0.0.18.dist-info/METADATA
locklib-0.0.18.dist-info/WHEEL
locklib-0.0.18.dist-info/top_level.txt
locklib-0.0.18.dist-info/RECORD
